aquacropeto/__init__.py
aquacropeto/_check.py
aquacropeto/convert.py
aquacropeto/fao.py
aquacropeto/thornthwaite.py
aquacropeto-0.1.0.dist-info/LICENSE.txt
aquacropeto-0.1.0.dist-info/METADATA
aquacropeto-0.1.0.dist-info/WHEEL
aquacropeto-0.1.0.dist-info/top_level.txt
aquacropeto-0.1.0.dist-info/RECORD
